{
 "info": {
  "alerts": [
   {
    "annotations": {
     "summary": "a install down"
    },
    "endsAt": "0001-01-01T00:00:00Z",
    "generatorURL": "http://vb:9090/graph?g0.expr=up+%3D%3D+0\u0026g0.tab=1",
    "labels": {
     "alertname": "InstanceDown",
     "instance": "127.0.0.1:9100",
     "job": "node",
     "serverity": "danger"
    },
    "startsAt": "2019-04-16T17:02:38.665767154+07:00",
    "status": "firing"
   }
  ],
  "commonAnnotations": {
   "summary": "a install down"
  },
  "commonLabels": {
   "alertname": "InstanceDown",
   "instance": "127.0.0.1:9100",
   "job": "node",
   "serverity": "danger"
  },
  "externalURL": "http://vb:9093",
  "groupLabels": {
   "alertname": "InstanceDown"
  },
  "receiver": "elastic",
  "status": "firing",
  "version": "4",
  "groupKey": "{}/{serverity=\"danger\"}:{alertname=\"InstanceDown\"}"
 },
 "PastData": {
  "status": "success",
  "Data": {
   "resultType": "matrix",
   "Result": [
    {
     "Metric": {
      "__name__": "node_memory_MemFree_bytes",
      "instance": "127.0.0.1:9100",
      "job": "node"
     },
     "values": [
      {
       "timestamp": 1555408658000,
       "value": 302096384
      },
      {
       "timestamp": 1555408673000,
       "value": 302387200
      },
      {
       "timestamp": 1555408688000,
       "value": 304685056
      },
      {
       "timestamp": 1555408703000,
       "value": 303030272
      },
      {
       "timestamp": 1555408718000,
       "value": 302354432
      },
      {
       "timestamp": 1555408733000,
       "value": 296415232
      },
      {
       "timestamp": 1555408748000,
       "value": 292057088
      },
      {
       "timestamp": 1555408763000,
       "value": 295219200
      },
      {
       "timestamp": 1555408778000,
       "value": 304656384
      },
      {
       "timestamp": 1555408793000,
       "value": 297271296
      },
      {
       "timestamp": 1555408808000,
       "value": 298270720
      },
      {
       "timestamp": 1555408823000,
       "value": 293240832
      },
      {
       "timestamp": 1555408838000,
       "value": 293978112
      },
      {
       "timestamp": 1555408853000,
       "value": 287838208
      },
      {
       "timestamp": 1555408868000,
       "value": 290390016
      },
      {
       "timestamp": 1555408883000,
       "value": 283430912
      },
      {
       "timestamp": 1555408898000,
       "value": 280580096
      },
      {
       "timestamp": 1555408913000,
       "value": 275439616
      }
     ]
    }
   ]
  }
 }
}{
 "info": {
  "alerts": [
   {
    "annotations": {
     "summary": "a install down"
    },
    "endsAt": "2019-04-16T17:04:38.665767154+07:00",
    "generatorURL": "http://vb:9090/graph?g0.expr=up+%3D%3D+0\u0026g0.tab=1",
    "labels": {
     "alertname": "InstanceDown",
     "instance": "127.0.0.1:9100",
     "job": "node",
     "serverity": "danger"
    },
    "startsAt": "2019-04-16T17:02:38.665767154+07:00",
    "status": "resolved"
   }
  ],
  "commonAnnotations": {
   "summary": "a install down"
  },
  "commonLabels": {
   "alertname": "InstanceDown",
   "instance": "127.0.0.1:9100",
   "job": "node",
   "serverity": "danger"
  },
  "externalURL": "http://vb:9093",
  "groupLabels": {
   "alertname": "InstanceDown"
  },
  "receiver": "elastic",
  "status": "resolved",
  "version": "4",
  "groupKey": "{}/{serverity=\"danger\"}:{alertname=\"InstanceDown\"}"
 },
 "PastData": {
  "status": "success",
  "Data": {
   "resultType": "matrix",
   "Result": [
    {
     "Metric": {
      "__name__": "node_memory_MemFree_bytes",
      "instance": "127.0.0.1:9100",
      "job": "node"
     },
     "values": [
      {
       "timestamp": 1555408658000,
       "value": 302096384
      },
      {
       "timestamp": 1555408673000,
       "value": 302387200
      },
      {
       "timestamp": 1555408688000,
       "value": 304685056
      },
      {
       "timestamp": 1555408703000,
       "value": 303030272
      },
      {
       "timestamp": 1555408718000,
       "value": 302354432
      },
      {
       "timestamp": 1555408733000,
       "value": 296415232
      },
      {
       "timestamp": 1555408748000,
       "value": 292057088
      },
      {
       "timestamp": 1555408763000,
       "value": 295219200
      },
      {
       "timestamp": 1555408778000,
       "value": 304656384
      },
      {
       "timestamp": 1555408793000,
       "value": 297271296
      },
      {
       "timestamp": 1555408808000,
       "value": 298270720
      },
      {
       "timestamp": 1555408823000,
       "value": 293240832
      },
      {
       "timestamp": 1555408838000,
       "value": 293978112
      },
      {
       "timestamp": 1555408853000,
       "value": 287838208
      },
      {
       "timestamp": 1555408868000,
       "value": 290390016
      },
      {
       "timestamp": 1555408883000,
       "value": 283430912
      },
      {
       "timestamp": 1555408898000,
       "value": 280580096
      },
      {
       "timestamp": 1555408913000,
       "value": 275439616
      }
     ]
    }
   ]
  }
 }
}{
 "info": {
  "alerts": [
   {
    "annotations": {
     "summary": "a install down"
    },
    "endsAt": "0001-01-01T00:00:00Z",
    "generatorURL": "http://vb:9090/graph?g0.expr=up+%3D%3D+0\u0026g0.tab=1",
    "labels": {
     "alertname": "InstanceDown",
     "instance": "127.0.0.1:9100",
     "job": "node",
     "serverity": "danger"
    },
    "startsAt": "2019-04-16T17:06:08.665767154+07:00",
    "status": "firing"
   }
  ],
  "commonAnnotations": {
   "summary": "a install down"
  },
  "commonLabels": {
   "alertname": "InstanceDown",
   "instance": "127.0.0.1:9100",
   "job": "node",
   "serverity": "danger"
  },
  "externalURL": "http://vb:9093",
  "groupLabels": {
   "alertname": "InstanceDown"
  },
  "receiver": "elastic",
  "status": "firing",
  "version": "4",
  "groupKey": "{}/{serverity=\"danger\"}:{alertname=\"InstanceDown\"}"
 },
 "PastData": {
  "status": "success",
  "Data": {
   "resultType": "matrix",
   "Result": [
    {
     "Metric": {
      "__name__": "node_memory_MemFree_bytes",
      "instance": "127.0.0.1:9100",
      "job": "node"
     },
     "values": [
      {
       "timestamp": 1555408868000,
       "value": 290390016
      },
      {
       "timestamp": 1555408883000,
       "value": 283430912
      },
      {
       "timestamp": 1555408898000,
       "value": 280580096
      },
      {
       "timestamp": 1555408913000,
       "value": 275439616
      },
      {
       "timestamp": 1555409078000,
       "value": 268214272
      },
      {
       "timestamp": 1555409093000,
       "value": 267780096
      },
      {
       "timestamp": 1555409108000,
       "value": 272691200
      },
      {
       "timestamp": 1555409123000,
       "value": 271626240
      }
     ]
    }
   ]
  }
 }
}